.editorconfig
.gitignore
.gitlab-ci.yml
AUTHORS.rst
CONTRIBUTING.rst
HISTORY.rst
ISSUE_TEMPLATE.md
LICENSE
MANIFEST.in
Makefile
README.md
README.rst
environment.yml
polymer_env.yml
requirements.txt
requirements_dev.txt
setup.cfg
setup.py
tox.ini
acwater/__init__.py
acwater/acwater.py
acwater/cli.py
acwater/enpt_config.py
acwater/level1_enmap.py
acwater/polymer_enmap.py
acwater/writer.py
acwater.egg-info/PKG-INFO
acwater.egg-info/SOURCES.txt
acwater.egg-info/dependency_links.txt
acwater.egg-info/entry_points.txt
acwater.egg-info/not-zip-safe
acwater.egg-info/top_level.txt
docs/Makefile
docs/acwater.rst
docs/authors.rst
docs/conf.py
docs/contributing.rst
docs/history.rst
docs/index.rst
docs/installation.rst
docs/instructions_dev.rst
docs/make.bat
docs/modules.rst
docs/readme.rst
docs/tutorial.rst
docs/usage.rst
sciadrive/__init__.py
sciadrive/build_ascii.py
sciadrive/example_ascii.py
sciadrive/extraction_reshape.csv
sciadrive/reshape_spektrum.py