Metadata-Version: 2.1
Name: acwater
Version: 0.3.2
Summary: Atmospheric correction of EnMAP satellite data over water using Polymer algorithm
Home-page: https://gitlab.awi.de/phytooptics/acwater
Author: Leonado Alvarado
Author-email: leonardo.alvarado@awi.de
License: GNU General Public License v3
Keywords: acwater
Classifier: Development Status :: 2 - Pre-Alpha
Classifier: Intended Audience :: Developers
Classifier: License :: OSI Approved :: GNU General Public License v3 (GPLv3)
Classifier: Natural Language :: English
Classifier: Programming Language :: Python :: 3
Classifier: Programming Language :: Python :: 3.5
Classifier: Programming Language :: Python :: 3.6
Classifier: Programming Language :: Python :: 3.7
Classifier: Programming Language :: Python :: 3.8
Requires-Python: >=3.5
License-File: LICENSE
License-File: AUTHORS.rst
